setup.py
CrowdProcess.egg-info/PKG-INFO
CrowdProcess.egg-info/SOURCES.txt
CrowdProcess.egg-info/dependency_links.txt
CrowdProcess.egg-info/requires.txt
CrowdProcess.egg-info/top_level.txt
crowdprocess/__init__.py
crowdprocess/crowdprocess.py