Metadata-Version: 1.0
Name: CrowdProcess
Version: 0.2.0
Summary: UNKNOWN
Home-page: https://github.com/CrowdProcess/crpy
Author: João Jerónimo
Author-email: jj@crowdprocess.com
License: MIT
Platform: UNKNOWN
